PythonMarkdown/__init__.py
python_markdown-0.1.0.dist-info/licenses/LICENSE
python_markdown-0.1.0.dist-info/METADATA
python_markdown-0.1.0.dist-info/WHEEL
python_markdown-0.1.0.dist-info/top_level.txt
python_markdown-0.1.0.dist-info/RECORD
