Metadata-Version: 2.4
Name: python-markdown
Version: 0.1.0
Summary: A Python Markdown parser and converter
Home-page: https://github.com/almushafe/python-markdown.git
Author: almushafe
Author-email: your.email@example.com
License: MIT
Classifier: Programming Language :: Python :: 3
Classifier: License :: OSI Approved :: MIT License
Classifier: Operating System :: OS Independent
Classifier: Development Status :: 2 - Pre-Alpha
Classifier: Intended Audience :: Developers
Classifier: Topic :: Text Processing :: Markup :: Markdown
Requires-Python: >=3.6
License-File: LICENSE
Dynamic: license-file
